api/__init__.py
api/feedbacks.py
api/news.py
api/users.py
models/__init__.py
models/feedback.py
models/news.py
models/user.py
flask_backend_package-1.0.0.dist-info/METADATA
flask_backend_package-1.0.0.dist-info/WHEEL
flask_backend_package-1.0.0.dist-info/top_level.txt
flask_backend_package-1.0.0.dist-info/RECORD
